setup.py
streamlit_lightweight_charts_pro/__init__.py
streamlit_lightweight_charts_pro/cli.py
streamlit_lightweight_charts_pro/component.py
streamlit_lightweight_charts_pro/exceptions.py
streamlit_lightweight_charts_pro/logging_config.py
streamlit_lightweight_charts_pro/charts/__init__.py
streamlit_lightweight_charts_pro/charts/chart.py
streamlit_lightweight_charts_pro/charts/chart_manager.py
streamlit_lightweight_charts_pro/charts/series_settings_api.py
streamlit_lightweight_charts_pro/charts/options/__init__.py
streamlit_lightweight_charts_pro/charts/options/base_options.py
streamlit_lightweight_charts_pro/charts/options/chart_options.py
streamlit_lightweight_charts_pro/charts/options/interaction_options.py
streamlit_lightweight_charts_pro/charts/options/layout_options.py
streamlit_lightweight_charts_pro/charts/options/line_options.py
streamlit_lightweight_charts_pro/charts/options/localization_options.py
streamlit_lightweight_charts_pro/charts/options/price_format_options.py
streamlit_lightweight_charts_pro/charts/options/price_line_options.py
streamlit_lightweight_charts_pro/charts/options/price_scale_options.py
streamlit_lightweight_charts_pro/charts/options/sync_options.py
streamlit_lightweight_charts_pro/charts/options/time_scale_options.py
streamlit_lightweight_charts_pro/charts/options/trade_visualization_options.py
streamlit_lightweight_charts_pro/charts/options/ui_options.py
streamlit_lightweight_charts_pro/charts/series/__init__.py
streamlit_lightweight_charts_pro/charts/series/area.py
streamlit_lightweight_charts_pro/charts/series/band.py
streamlit_lightweight_charts_pro/charts/series/bar_series.py
streamlit_lightweight_charts_pro/charts/series/base.py
streamlit_lightweight_charts_pro/charts/series/baseline.py
streamlit_lightweight_charts_pro/charts/series/candlestick.py
streamlit_lightweight_charts_pro/charts/series/gradient_ribbon.py
streamlit_lightweight_charts_pro/charts/series/histogram.py
streamlit_lightweight_charts_pro/charts/series/line.py
streamlit_lightweight_charts_pro-0.1.6.dist-info/licenses/LICENSE
streamlit_lightweight_charts_pro-0.1.6.dist-info/METADATA
streamlit_lightweight_charts_pro-0.1.6.dist-info/WHEEL
streamlit_lightweight_charts_pro-0.1.6.dist-info/entry_points.txt
streamlit_lightweight_charts_pro-0.1.6.dist-info/top_level.txt
streamlit_lightweight_charts_pro-0.1.6.dist-info/RECORD
